filatt/__init__.py
filatt/filatt.py
filatt_karjakak-0.2.0.dist-info/METADATA
filatt_karjakak-0.2.0.dist-info/WHEEL
filatt_karjakak-0.2.0.dist-info/entry_points.txt
filatt_karjakak-0.2.0.dist-info/top_level.txt
filatt_karjakak-0.2.0.dist-info/RECORD
