Metadata-Version: 2.1
Name: filatt-karjakak
Version: 0.2.0
Summary: Change a file attributes for Windows
Home-page: https://github.com/kakkarja/WinAtt
Author: karjakak
Author-email: kakkarja.github@gmail.com
License: BSD3 License
Platform: UNKNOWN
Classifier: Environment :: Win32 (MS Windows)
Classifier: Programming Language :: Python :: 3.10
Classifier: License :: OSI Approved :: BSD License
Requires-Python: >=3.10
